{"chunk_definitions":[{"chunk_id":"csetup_chunk","chunk_label":"setup","document_id":"299DE019","expansion_state":0,"options":{"engine":"r","include":false,"label":"setup"},"row":9,"row_count":1,"visible":true},{"chunk_id":"cf9h66gdz47tg","chunk_label":"load_pkgs","document_id":"299DE019","expansion_state":0,"options":{"engine":"r","include":false,"label":"load_pkgs","message":false,"results":"hide","warning":false},"row":16,"row_count":1,"visible":true},{"chunk_id":"c08u4gz99ro4a","chunk_label":"data_locations","document_id":"299DE019","expansion_state":0,"options":{"engine":"r","label":"data_locations"},"row":26,"row_count":1,"visible":true},{"chunk_id":"c57wyuy775lpw","chunk_label":"read_in","document_id":"299DE019","expansion_state":0,"options":{"engine":"r","label":"read_in"},"row":47,"row_count":1,"visible":true},{"chunk_id":"cfpncg9lz4mpp","chunk_label":"unnamed-chunk-1","document_id":"299DE019","expansion_state":0,"options":{"engine":"r","label":"unnamed-chunk-29"},"row":69,"row_count":1,"visible":true},{"chunk_id":"c6gg8s1pf9ena","chunk_label":"unnamed-chunk-2","document_id":"299DE019","expansion_state":0,"options":{"engine":"r","label":"unnamed-chunk-39"},"row":82,"row_count":1,"visible":true},{"chunk_id":"cx2mb8tieqjnu","chunk_label":"unnamed-chunk-3","document_id":"299DE019","expansion_state":0,"options":{"engine":"r","label":"unnamed-chunk-37"},"row":110,"row_count":1,"visible":true},{"chunk_id":"c1actpye2ughw","chunk_label":"unnamed-chunk-4","document_id":"299DE019","expansion_state":0,"options":{"engine":"r","label":"unnamed-chunk-40"},"row":137,"row_count":1,"visible":true},{"chunk_id":"cmtcfqq8pcivy","chunk_label":"unnamed-chunk-5","document_id":"299DE019","expansion_state":0,"options":{"engine":"r","label":"unnamed-chunk-34"},"row":160,"row_count":1,"visible":true}],"chunk_rendered_width":529,"default_chunk_options":{"echo":true,"error":false},"doc_write_time":1542321338,"working_dir":null}